{
  "entity": "performance_summary",
  "updated": "2026-07-14",
  "model_version": "v1.0",
  "note": "Aggregate performance only \u2014 no individual picks, lines, odds, or bet dates are exported here. See performance_tracker.py for the private, full-detail source this was generated from.",
  "overall": {
    "record": {
      "value": "81-36",
      "source": "performance_tracker",
      "confidence": "high"
    },
    "win_rate_pct": {
      "value": 69.2,
      "source": "performance_tracker",
      "confidence": "high"
    },
    "total_graded": {
      "value": 117,
      "source": "performance_tracker",
      "confidence": "high"
    }
  },
  "roi": {
    "roi_pct": {
      "value": 51.2,
      "source": "performance_tracker",
      "confidence": "high"
    },
    "profit_units": {
      "value": 47.12,
      "source": "performance_tracker",
      "confidence": "high"
    },
    "picks_used": {
      "value": 92,
      "source": "performance_tracker",
      "confidence": "high"
    },
    "picks_skipped_no_odds": {
      "value": 25,
      "source": "performance_tracker",
      "confidence": "high"
    },
    "clv": {
      "value": null,
      "source": "performance_tracker",
      "confidence": "high"
    }
  },
  "by_sport": [
    {
      "sport": "wnba",
      "record": {
        "value": "48-22",
        "source": "performance_tracker",
        "confidence": "high"
      },
      "win_rate_pct": {
        "value": 68.6,
        "source": "performance_tracker",
        "confidence": "high"
      }
    },
    {
      "sport": "mlb",
      "record": {
        "value": "28-14",
        "source": "performance_tracker",
        "confidence": "high"
      },
      "win_rate_pct": {
        "value": 66.7,
        "source": "performance_tracker",
        "confidence": "high"
      }
    },
    {
      "sport": "nba",
      "record": {
        "value": "5-0",
        "source": "performance_tracker",
        "confidence": "high"
      },
      "win_rate_pct": {
        "value": 100.0,
        "source": "performance_tracker",
        "confidence": "high"
      }
    }
  ],
  "confidence_calibration": [
    {
      "bucket": "75-79%",
      "record": {
        "value": "1-0",
        "source": "performance_tracker",
        "confidence": "high"
      },
      "actual_win_rate_pct": {
        "value": 100.0,
        "source": "performance_tracker",
        "confidence": "high"
      }
    }
  ]
}